{
  "id": "kaiserschlacht",
  "title": "Kaiserschlacht",
  "description": "Kaiserschlacht is a World War I horror RPG currently in the playtesting phase.",
  "authors": [
    {
      "name": "M. Okonsky",
      "discord": "mokonsky"
    }
  ],
  "url": "https://github.com/mokonsky/Kaiserschlacht",
  "license": "LICENSE.txt",
  "readme": "README.md",
  "bugs": "https://github.com/mokonsky/Kaiserschlacht/issues",
  "changelog": "CHANGELOG.md",
  "version": "0.4.28",
  "compatibility": {
    "minimum": 11,
    "verified": "12.325",
    "maximum": 12
  },
  "esmodules": ["module/kaiserschlacht.mjs"],
  "scripts": ["lib/tagify.min.js", "lib/sortable.core.esm.js"],
  "styles": ["styles/kaiserschlacht.css"],
  "languages": [
    {
      "lang": "en",
      "name": "English",
      "path": "lang/en.json"
    }
  ],
  "packs": [
    {
      "name": "npcs",
      "label": "NPCs",
      "path": "packs/npcs",
      "type": "Actor",
      "ownership": {
        "PLAYER": "OBSERVER",
        "ASSISTANT": "OWNER"
      },
      "system": "kaiserschlacht",
      "flags": {}
    },
    {
      "name": "characters",
      "label": "Characters",
      "path": "packs/characters",
      "type": "Actor",
      "ownership": {
        "PLAYER": "OBSERVER",
        "ASSISTANT": "OWNER"
      },
      "system": "kaiserschlacht",
      "flags": {}
    },
    {
      "name": "features",
      "label": "Features",
      "path": "packs/features",
      "type": "Item",
      "ownership": {
        "PLAYER": "OBSERVER",
        "ASSISTANT": "OWNER"
      },
      "system": "kaiserschlacht",
      "flags": {}
    },
    {
      "name": "weapons",
      "label": "Weapons",
      "path": "packs/weapons",
      "type": "Item",
      "ownership": {
        "PLAYER": "OBSERVER",
        "ASSISTANT": "OWNER"
      },
      "system": "kaiserschlacht",
      "flags": {}
    },
    {
      "name": "armor",
      "label": "Armor",
      "path": "packs/armor",
      "type": "Item",
      "ownership": {
        "PLAYER": "OBSERVER",
        "ASSISTANT": "OWNER"
      },
      "system": "kaiserschlacht",
      "flags": {}
    },
    {
      "name": "items",
      "label": "Items",
      "path": "packs/items",
      "type": "Item",
      "ownership": {
        "PLAYER": "OBSERVER",
        "ASSISTANT": "OWNER"
      },
      "system": "kaiserschlacht",
      "flags": {}
    },
    {
      "name": "macros",
      "label": "Macros",
      "path": "packs/macros",
      "type": "Macro",
      "ownership": {
        "PLAYER": "OBSERVER",
        "ASSISTANT": "OWNER"
      },
      "system": "kaiserschlacht",
      "flags": {}
    },
    {
      "name": "journal",
      "label": "Journal",
      "path": "packs/journal",
      "type": "JournalEntry",
      "ownership": {
        "PLAYER": "OBSERVER",
        "ASSISTANT": "OWNER"
      },
      "system": "kaiserschlacht",
      "flags": {}
    }
  ],
  "packFolders": [],
  "socket": false,
  "manifest": "https://github.com/mokonsky/Kaiserschlacht/releases/latest/download/system.json",
  "download": "https://github.com/mokonsky/Kaiserschlacht/releases/latest/download/Kaiserschlacht.zip",
  "gridDistance": 1,
  "gridUnits": "sq",
  "primaryTokenAttribute": "health",
  "secondaryTokenAttribute": ""
}
